MANIFEST.in
README.md
setup.py
qtpyt/__init__.py
qtpyt/basis.py
qtpyt/bond_current.py
qtpyt/continued_fraction.py
qtpyt/tightbinding.py
qtpyt/tools.py
qtpyt.egg-info/PKG-INFO
qtpyt.egg-info/SOURCES.txt
qtpyt.egg-info/dependency_links.txt
qtpyt.egg-info/entry_points.txt
qtpyt.egg-info/not-zip-safe
qtpyt.egg-info/requires.txt
qtpyt.egg-info/top_level.txt
qtpyt/.vscode/settings.json
qtpyt/base/__init__.py
qtpyt/base/_kernels.py
qtpyt/base/greenfunction.py
qtpyt/base/intgreenfunction.py
qtpyt/base/leads.py
qtpyt/base/selfenergy.py
qtpyt/base/test_kernels.py
qtpyt/base/.vscode/settings.json
qtpyt/block_tridiag/__init__.py
qtpyt/block_tridiag/btmatrix.py
qtpyt/block_tridiag/graph_partition.py
qtpyt/block_tridiag/greenfunction.py
qtpyt/block_tridiag/recursive.py
qtpyt/block_tridiag/solvers.py
qtpyt/block_tridiag/theory.ipynb
qtpyt/block_tridiag/.ipynb_checkpoints/Untitled-checkpoint.ipynb
qtpyt/block_tridiag/.ipynb_checkpoints/theory-checkpoint.ipynb
qtpyt/block_tridiag/.vscode/settings.json
qtpyt/kernels/__init__.py
qtpyt/kernels/hs_cpu.py
qtpyt/kernels/hs_gpu.py
qtpyt/kernels/linalg_cpu.py
qtpyt/kernels/linalg_gpu.py
qtpyt/kernels/test_linalg_cpu.py
qtpyt/kernels/test_linalg_gpu.py
qtpyt/kernels/.vscode/settings.json
qtpyt/kernels/__pycache__/hs_cpu._geamC-11.py37m.1.nbc
qtpyt/kernels/__pycache__/hs_cpu._geamC-11.py37m.nbi
qtpyt/kernels/__pycache__/hs_cpu._geamC-12.py37m.1.nbc
qtpyt/kernels/__pycache__/hs_cpu._geamC-12.py37m.nbi
qtpyt/kernels/__pycache__/hs_cpu._geamT-4.py37m.1.nbc
qtpyt/kernels/__pycache__/hs_cpu._geamT-4.py37m.nbi
qtpyt/kernels/__pycache__/hs_cpu._geamT-5.py37m.1.nbc
qtpyt/kernels/__pycache__/hs_cpu._geamT-5.py37m.nbi
qtpyt/kernels/__pycache__/hs_cpu._get_lambda-18.py37m.1.nbc
qtpyt/kernels/__pycache__/hs_cpu._get_lambda-18.py37m.nbi
qtpyt/kernels/__pycache__/hs_cpu._get_lambda-19.py37m.1.nbc
qtpyt/kernels/__pycache__/hs_cpu._get_lambda-19.py37m.nbi
qtpyt/lo/__init__.py
qtpyt/lo/block_inv.py
qtpyt/lo/coupledhamiltonian.py
qtpyt/lo/test_tools.py
qtpyt/lo/tk_gpaw.py
qtpyt/lo/tools.py
qtpyt/surface/Develop.ipynb
qtpyt/surface/__init__.py
qtpyt/surface/_recursive.c
qtpyt/surface/_recursive.pyx
qtpyt/surface/_unfold_numba.py
qtpyt/surface/kpts.py
