Metadata-Version: 1.2
Name: qtpyt
Version: 0.5.3
Summary:  qtpyt is the a python package for quantum transport simulations.
Home-page: https://gitlab.ethz.ch/ggandus/qtpyt.git
Author: Guido Gandus
Author-email: ggandus@ethz.ch
License: Apache 2.0
Platform: any
Requires-Python: >= 3.7
